Metadata-Version: 2.4
Name: adafruit-circuitpython-color-terminal
Version: 0.2.1
Summary: Extension of terminalio.Terminal that supports ANSI color escapes for subsets of the text
Author-email: Adafruit Industries <circuitpython@adafruit.com>
License: MIT
Project-URL: Homepage, https://github.com/adafruit/Adafruit_CircuitPython_Color_Terminal
Keywords: adafruit,blinka,circuitpython,micropython,color_terminal,ANSI,Colors,Color,Terminal,EscapeCode,EscapeCodes,Console
Classifier: Intended Audience :: Developers
Classifier: Topic :: Software Development :: Libraries
Classifier: Topic :: Software Development :: Embedded Systems
Classifier: Topic :: System :: Hardware
Classifier: License :: OSI Approved :: MIT License
Classifier: Programming Language :: Python :: 3
License-File: LICENSE
Requires-Dist: Adafruit-Blinka
Provides-Extra: optional
Dynamic: license-file
